testrail_reporter/__init__.py
testrail_reporter/cmd/__init__.py
testrail_reporter/cmd/reporter.py
testrail_reporter/etc/attrs2id.yaml
testrail_reporter/etc/check_list_example.yml
testrail_reporter/etc/tr_case_attrs.yaml
testrail_reporter/etc/tr_result_attrs.yaml
testrail_reporter/etc/maps/locust/case_template.yaml
testrail_reporter/etc/maps/locust/result_template.yaml
testrail_reporter/etc/maps/pytest/case_template.yaml
testrail_reporter/etc/maps/pytest/result_template.yaml
testrail_reporter/etc/maps/tempest/case_template.yaml
testrail_reporter/etc/maps/tempest/result_template.yaml
testrail_reporter/lib/__init__.py
testrail_reporter/lib/actions.py
testrail_reporter/lib/config.py
testrail_reporter/lib/csv_parser.py
testrail_reporter/lib/dynamic_parser.py
testrail_reporter/lib/exceptions.py
testrail_reporter/lib/reportparser.py
testrail_reporter/lib/settings.py
testrail_reporter/lib/testcaseparser.py
testrail_reporter/lib/testrail.py
testrail_reporter/lib/testrailanalyzer.py
testrail_reporter/lib/testrailproject.py
testrail_reporter/lib/testrailreporter.py
testrail_reporter/lib/xml_parser.py
testrail_reporter_tool-1.4.0.dist-info/LICENSE.txt
testrail_reporter_tool-1.4.0.dist-info/METADATA
testrail_reporter_tool-1.4.0.dist-info/WHEEL
testrail_reporter_tool-1.4.0.dist-info/entry_points.txt
testrail_reporter_tool-1.4.0.dist-info/top_level.txt
testrail_reporter_tool-1.4.0.dist-info/RECORD
