Metadata-Version: 2.1
Name: testrail-reporter-tool
Version: 1.4.0
Summary: TestRail reporter tool
Home-page: https://github.com/ibumarskov/testrail-reporter
Author: Ilya Bumarskov
Author-email: bumarskov@gmail.com
Keywords: testrail reporter pytest tempest
Classifier: Development Status :: 2 - Pre-Alpha
Classifier: Topic :: Software Development :: Quality Assurance
Classifier: License :: OSI Approved :: MIT License
Classifier: Programming Language :: Python :: 3
Classifier: Programming Language :: Python :: 3.6
Classifier: Programming Language :: Python :: 3 :: Only
Requires-Python: >=3.6
License-File: LICENSE.txt
Requires-Dist: flake8
Requires-Dist: pyyaml
Requires-Dist: tox
Requires-Dist: wheel
Requires-Dist: requests
